MANIFEST.in
README.md
setup.py
pybytecode/__init__.py
pybytecode/bytecode.py
pybytecode/codegen.py
pybytecode/fibonacci.py
pybytecode.egg-info/PKG-INFO
pybytecode.egg-info/SOURCES.txt
pybytecode.egg-info/dependency_links.txt
pybytecode.egg-info/entry_points.txt
pybytecode.egg-info/top_level.txt