Metadata-Version: 1.1
Name: pybytecode
Version: 0.1
Summary: A Python bytecode compiler and bytecode generator.
Home-page: https://github.com/Risto-Stevcev/pybytecode
Author: Risto Stevcev
Author-email: risto1@gmail.com
License: BSD
Keywords: compiler bytecode python code
Platform: UNKNOWN
Classifier: Development Status :: 5 - Production/Stable
Classifier: Environment :: Console
Classifier: Intended Audience :: Developers
Classifier: License :: OSI Approved :: BSD License
Classifier: Natural Language :: English
Classifier: Operating System :: OS Independent
Classifier: Programming Language :: Python :: 3
Classifier: Programming Language :: Python :: 2.7
Classifier: Topic :: Software Development :: Assemblers
Classifier: Topic :: Software Development :: Code Generators
Classifier: Topic :: Software Development :: Compilers
Classifier: Topic :: Software Development :: Disassemblers
